pymercure/__init__.py
pymercure/consumer.py
pymercure/exceptions.py
pymercure/message.py
pymercure/setup.py
pymercure/tests.py
pymercure/publisher/__init__.py
pymercure/publisher/async.py
pymercure/publisher/publisher.py
pymercure/publisher/sync.py
pymercure-0.0.1.0.dist-info/DESCRIPTION.rst
pymercure-0.0.1.0.dist-info/METADATA
pymercure-0.0.1.0.dist-info/RECORD
pymercure-0.0.1.0.dist-info/WHEEL
pymercure-0.0.1.0.dist-info/metadata.json
pymercure-0.0.1.0.dist-info/top_level.txt
