Metadata-Version: 2.0
Name: pymercure
Version: 0.0.1.0
Summary: Python Mercure library
Home-page: https://github.com/vitorluis/python-mercure
Author: Vitor Villar
Author-email: vitor.luis98@gmail.com
License: BSD
Platform: any
Classifier: Environment :: Web Environment
Classifier: Intended Audience :: Developers
Classifier: License :: OSI Approved :: BSD License
Classifier: Operating System :: OS Independent
Classifier: Programming Language :: Python
Classifier: Programming Language :: Python :: 3
Classifier: Topic :: Internet :: WWW/HTTP :: Dynamic Content
Classifier: Topic :: Software Development :: Libraries :: Python Modules
Requires-Dist: grequests
Requires-Dist: requests
Requires-Dist: sseclient-py
